supernotelib/__init__.py
supernotelib/color.py
supernotelib/converter.py
supernotelib/decoder.py
supernotelib/exceptions.py
supernotelib/fileformat.py
supernotelib/manipulator.py
supernotelib/parser.py
supernotelib/utils.py
supernotelib/cmds/__init__.py
supernotelib/cmds/supernote_fuse.py
supernotelib/cmds/supernote_tool.py
supernotelib-0.6.4.dist-info/METADATA
supernotelib-0.6.4.dist-info/WHEEL
supernotelib-0.6.4.dist-info/entry_points.txt
supernotelib-0.6.4.dist-info/licenses/LICENSE
supernotelib-0.6.4.dist-info/RECORD
