Metadata-Version: 2.4
Name: supernotelib
Version: 0.6.4
Summary: An unofficial converter library for Ratta Supernote
Project-URL: homepage, https://github.com/jya-dev/supernote-tool
Author-email: jya <jya@wizmy.net>
License:                                  Apache License
License-File: LICENSE
Keywords: supernote
Classifier: Development Status :: 4 - Beta
Classifier: Intended Audience :: Developers
Classifier: Intended Audience :: End Users/Desktop
Classifier: License :: OSI Approved :: Apache Software License
Classifier: Operating System :: OS Independent
Classifier: Programming Language :: Python
Classifier: Programming Language :: Python :: 3 :: Only
Classifier: Programming Language :: Python :: 3.6
Classifier: Programming Language :: Python :: 3.7
Classifier: Programming Language :: Python :: 3.8
Classifier: Programming Language :: Python :: 3.9
Classifier: Programming Language :: Python :: 3.10
Classifier: Topic :: Multimedia :: Graphics
Classifier: Topic :: Multimedia :: Graphics :: Graphics Conversion
Classifier: Topic :: Utilities
Requires-Python: >=3.6
Requires-Dist: colour>=0.1.5
Requires-Dist: fusepy>=3.0.1
Requires-Dist: numpy>=1.19.0
Requires-Dist: pillow>=7.2.0
Requires-Dist: potracer>=0.0.1
Requires-Dist: pypng>=0.0.20
Requires-Dist: reportlab>=3.6.1
Requires-Dist: svglib>=1.1.0
Requires-Dist: svgwrite>=1.4
